{
  "story_nodes": {
    "nodes": [
      {
        "description": "Ratios Story 2 Node 1",
        "exploration_id": "k2bQ7z5XHNbK",
        "destination_node_ids": [
          "node_2"
        ],
        "thumbnail_filename": "",
        "outline_is_finalized": false,
        "id": "node_1",
        "prerequisite_skill_ids": [],
        "thumbnail_bg_color": "#F68F78",
        "exp_summary_dict": {
          "thumbnail_bg_color": "#e28453",
          "title": "Ratios-3",
          "language_code": "en",
          "objective": "Learn about equivalent ratios",
          "id": "k2bQ7z5XHNbK"
        },
        "outline": "",
        "title": "Equivalent Ratios",
        "acquired_skill_ids": []
      },
      {
        "description": "Ratios Story 2 Node 2",
        "exploration_id": "tIoSb3HZFN6e",
        "destination_node_ids": [],
        "thumbnail_filename": "",
        "outline_is_finalized": false,
        "id": "node_2",
        "prerequisite_skill_ids": [],
        "thumbnail_bg_color": "#F68F78",
        "exp_summary_dict": {
          "thumbnail_bg_color": "#e28453",
          "title": "Ratios-4",
          "language_code": "en",
          "objective": "Learn about simplest forms of ratios",
          "id": "tIoSb3HZFN6e"
        },
        "outline": "",
        "title": "Writing Ratios in Simplest Form",
        "acquired_skill_ids": []
      }
    ],
    "initial_node_id": "node_1",
    "next_node_id": "node_3"
  },
  "story_description": "",
  "story_title": "Ratios: Part 2"
}
